clamming/__init__.py
clamming/claminfo.py
clamming/claminfomd.py
clamming/clamsclass.py
clamming/clamspack.py
clamming/clamutils.py
clamming/classparser.py
clamming/html_export.py
Clamming-1.6.dist-info/AUTHORS
Clamming-1.6.dist-info/LICENSE
Clamming-1.6.dist-info/METADATA
Clamming-1.6.dist-info/WHEEL
Clamming-1.6.dist-info/top_level.txt
Clamming-1.6.dist-info/RECORD
